{
    "meta": {
        "code": 200,
        "requestId": "6765cbc8e1740370d841b293"
    },
    "notifications": [
        {
            "type": "notificationTray",
            "item": {
                "unreadCount": 0
            }
        }
    ],
    "response": {
        "venue": {
            "id": "4b600990f964a520e3d329e3",
            "name": "Shimbashi Station (\u65b0\u6a4b\u99c5)",
            "contact": {},
            "location": {
                "address": "\u65b0\u6a4b2/\u6771\u65b0\u6a4b1",
                "lat": 35.66617091085101,
                "lng": 139.75832361727953,
                "labeledLatLngs": [
                    {
                        "label": "display",
                        "lat": 35.66617091085101,
                        "lng": 139.75832361727953
                    }
                ],
                "radius50": 92,
                "radius90": 688,
                "postalCode": "105-0004",
                "cc": "JP",
                "neighborhood": "\u65b0\u6a4b",
                "city": "\u6771\u4eac",
                "state": "\u6771\u4eac\u90fd",
                "country": "\u65e5\u672c",
                "formattedAddress": [
                    "\u65b0\u6a4b2/\u6771\u65b0\u6a4b1",
                    "\u6e2f\u533a, \u6771\u4eac\u90fd",
                    "105-0004",
                    "\u65e5\u672c"
                ]
            },
            "canonicalUrl": "https://foursquare.com/v/%E6%96%B0%E6%A9%8B%E9%A7%85-shimbashi-sta/4b600990f964a520e3d329e3",
            "categories": [
                {
                    "id": "4bf58dd8d48988d129951735",
                    "name": "Rail Station",
                    "pluralName": "Rail Stations",
                    "shortName": "Rail Station",
                    "icon": {
                        "prefix": "https://ss3.4sqi.net/img/categories_v2/travel/trainstation_",
                        "suffix": ".png"
                    },
                    "categoryCode": 19047,
                    "mapIcon": "fsq-default",
                    "primary": true
                }
            ],
            "verified": false,
            "stats": {
                "tipCount": 65
            },
            "likes": {
                "count": 724,
                "groups": [
                    {
                        "type": "others",
                        "count": 724,
                        "items": []
                    }
                ],
                "summary": "724 Likes"
            },
            "like": false,
            "dislike": false,
            "ok": false,
            "header": "According to the Foursquare community, this place is a 6.3 out of 10.",
            "rating": 6.3,
            "ratingColor": "FFC800",
            "ratingSignals": 1325,
            "explanation": "We take into account visits and input from our community. You'll see a number on places based off of ratings and tips written by people like you.",
            "ratingCategory": "poor",
            "beenHere": {
                "count": 0,
                "unconfirmedCount": 0,
                "marked": false,
                "lastCheckinExpiredAt": 0
            },
            "photos": {
                "count": 5160,
                "groups": [
                    {
                        "type": "venue",
                        "name": "Venue photos",
                        "count": 5160,
                        "items": [
                            {
                                "id": "5a812d5a66fc6509b7544bf5",
                                "createdAt": 1518415194,
                                "source": {
                                    "name": "Swarm for iOS",
                                    "url": "https://www.swarmapp.com"
                                },
                                "prefix": "https://fastly.4sqi.net/img/general/",
                                "suffix": "/454721750_KNZ1sYqMcM5NQ8hlvoxeDeOQpHMwrBiofKcG7y9HHBk.jpg",
                                "width": 1440,
                                "height": 1920,
                                "user": {
                                    "id": "454721750",
                                    "firstName": "\u30d7\u30ea",
                                    "lastName": "\u30de\u30c0\u30e0",
                                    "handle": "madamu5139070",
                                    "privateProfile": false,
                                    "gender": "none",
                                    "countryCode": "JP",
                                    "followingRelationship": "none",
                                    "photo": {
                                        "prefix": "https://fastly.4sqi.net/img/user/",
                                        "suffix": "/454721750_Dltb0ZVy_O6-lOQDrqCd4TZU0iubSSNgzr6Kir-XkteZKnRbUK_Wxlnk8JVqbA57cQWM9zJjP.jpg"
                                    }
                                },
                                "visibility": "public"
                            },
                            {
                                "id": "56d8514c498ef276fcf3dcf1",
                                "createdAt": 1457017164,
                                "source": {
                                    "name": "Swarm for iOS",
                                    "url": "https://www.swarmapp.com"
                                },
                                "prefix": "https://fastly.4sqi.net/img/general/",
                                "suffix": "/4184449_wNQNNipz2MET5UBVn3Iiv5-TKFwvRTyELHkaaBYU90k.jpg",
                                "width": 1920,
                                "height": 1440,
                                "user": {
                                    "id": "4184449",
                                    "firstName": "Amm",
                                    "lastName": "Nutthaon",
                                    "handle": "ammn5939166",
                                    "privateProfile": false,
                                    "gender": "female",
                                    "address": "",
                                    "city": "",
                                    "state": "",
                                    "countryCode": "TH",
                                    "followingRelationship": "none",
                                    "photo": {
                                        "prefix": "https://fastly.4sqi.net/img/user/",
                                        "suffix": "/EVU4H3EHOGDX4XSH.jpg"
                                    }
                                },
                                "visibility": "public"
                            },
                            {
                                "id": "56b9849f498e8291757f5195",
                                "createdAt": 1454998687,
                                "source": {
                                    "name": "Swarm for iOS",
                                    "url": "https://www.swarmapp.com"
                                },
                                "prefix": "https://fastly.4sqi.net/img/general/",
                                "suffix": "/41547642_pQ0kul_3KDyJ1tWy_oWG-4i0cLVPhSQxUBzdDthf3xo.jpg",
                                "width": 1440,
                                "height": 1920,
                                "user": {
                                    "id": "41547642",
                                    "firstName": "Munenori",
                                    "lastName": "Fujiwara",
                                    "handle": "norikunny",
                                    "privateProfile": false,
                                    "gender": "male",
                                    "address": "",
                                    "city": "",
                                    "state": "",
                                    "countryCode": "JP",
                                    "followingRelationship": "none",
                                    "photo": {
                                        "prefix": "https://fastly.4sqi.net/img/user/",
                                        "suffix": "/41547642_Ev-S4s5S_WSOWM--9kV9e1X0U-f7RWVZYGUHx_FEAigusRTkPb_w5diHopMrzIbKIfcmyJBhj.jpg"
                                    }
                                },
                                "visibility": "public"
                            },
                            {
                                "id": "5a7ac7c4e96d0c127849cf34",
                                "createdAt": 1517995972,
                                "source": {
                                    "name": "Swarm for iOS",
                                    "url": "https://www.swarmapp.com"
                                },
                                "prefix": "https://fastly.4sqi.net/img/general/",
                                "suffix": "/2278802_x_bv3bNbkV94r6Ix8fRGcwXNChvwaCiJQOPoDCcuK4E.jpg",
                                "width": 1920,
                                "height": 1440,
                                "user": {
                                    "id": "2278802",
                                    "firstName": "Sohei",
                                    "lastName": "Miyoshi",
                                    "handle": "hummingbird1979",
                                    "privateProfile": false,
                                    "gender": "male",
                                    "countryCode": "JP",
                                    "followingRelationship": "none",
                                    "photo": {
                                        "prefix": "https://fastly.4sqi.net/img/user/",
                                        "suffix": "/GPJ2X5DXAB2OMMP3.jpg"
                                    }
                                },
                                "visibility": "public"
                            }
                        ]
                    }
                ]
            },
            "reasons": {
                "count": 1,
                "items": [
                    {
                        "summary": "Lots of people like this place",
                        "type": "general",
                        "reasonName": "rawLikesReason"
                    }
                ]
            },
            "createdAt": 1264585104,
            "hereNow": {
                "count": 0,
                "summary": "Nobody here",
                "groups": []
            },
            "tips": {
                "count": 65,
                "groups": [
                    {
                        "type": "following",
                        "name": "Tips from people you follow",
                        "count": 0,
                        "items": []
                    },
                    {
                        "type": "others",
                        "name": "All tips",
                        "count": 65,
                        "items": [
                            {
                                "id": "510fc102e4b048d891b92975",
                                "createdAt": 1359986946,
                                "text": "JR\u65b0\u6a4b\u99c5\u306e\u8a18\u5ff5\u30b9\u30bf\u30f3\u30d7\uff1a\u9ce5\u68ee\u53e3\u6539\u672d\u524d",
                                "type": "user",
                                "canonicalUrl": "https://foursquare.com/item/510fc102e4b048d891b92975",
                                "photo": {
                                    "id": "510fc10645b0250b28549452",
                                    "createdAt": 1359986950,
                                    "source": {
                                        "name": "Foursquare Web",
                                        "url": "https://foursquare.com"
                                    },
                                    "prefix": "https://fastly.4sqi.net/img/general/",
                                    "suffix": "/3551417_AK0h_4PtCUsXactdvZNUteajSjFlfkWEZUAyJg8vCxM.jpg",
                                    "width": 2592,
                                    "height": 1936,
                                    "visibility": "public"
                                },
                                "photos": [
                                    {
                                        "id": "510fc10645b0250b28549452",
                                        "createdAt": 1359986950,
                                        "source": {
                                            "name": "Foursquare Web",
                                            "url": "https://foursquare.com"
                                        },
                                        "prefix": "https://fastly.4sqi.net/img/general/",
                                        "suffix": "/3551417_AK0h_4PtCUsXactdvZNUteajSjFlfkWEZUAyJg8vCxM.jpg",
                                        "width": 2592,
                                        "height": 1936,
                                        "visibility": "public"
                                    }
                                ],
                                "photourl": "https://fastly.4sqi.net/img/general/original/3551417_AK0h_4PtCUsXactdvZNUteajSjFlfkWEZUAyJg8vCxM.jpg",
                                "lang": "ja",
                                "likes": {
                                    "count": 15,
                                    "groups": [
                                        {
                                            "type": "others",
                                            "count": 15,
                                            "items": []
                                        }
                                    ],
                                    "summary": "15 likes"
                                },
                                "like": false,
                                "logView": true,
                                "editedAt": 1360244012,
                                "agreeCount": 46,
                                "disagreeCount": 0,
                                "todo": {
                                    "count": 0
                                },
                                "user": {
                                    "id": "3551417",
                                    "firstName": "Miuko",
                                    "lastName": "H",
                                    "handle": "miuko",
                                    "privateProfile": false,
                                    "gender": "female",
                                    "countryCode": "TW",
                                    "followingRelationship": "none",
                                    "photo": {
                                        "prefix": "https://fastly.4sqi.net/img/user/",
                                        "suffix": "/FFOANJPP3NI4ZVIF.jpg"
                                    }
                                }
                            },
                            {
                                "id": "4b6ebab170c603bbbeb791b4",
                                "createdAt": 1265547953,
                                "text": "\u6a2a\u9808\u8cc0\u7dda\u306b\u304a\u308a\u308b\u30a8\u30b9\u30ab\u30ec\u30fc\u30bf\u9577\u3044",
                                "type": "user",
                                "canonicalUrl": "https://foursquare.com/item/4b6ebab170c603bbbeb791b4",
                                "lang": "ja",
                                "likes": {
                                    "count": 11,
                                    "groups": [
                                        {
                                            "type": "others",
                                            "count": 11,
                                            "items": []
                                        }
                                    ],
                                    "summary": "11 likes"
                                },
                                "like": false,
                                "logView": true,
                                "agreeCount": 11,
                                "disagreeCount": 0,
                                "todo": {
                                    "count": 1
                                },
                                "user": {
                                    "id": "264829",
                                    "firstName": "Ayumi",
                                    "lastName": "Ogura",
                                    "handle": "happi_tan",
                                    "privateProfile": false,
                                    "gender": "female",
                                    "countryCode": "JP",
                                    "followingRelationship": "none",
                                    "photo": {
                                        "prefix": "https://fastly.4sqi.net/img/user/",
                                        "suffix": "/EIOGPER4F5DAWFQB.gif"
                                    }
                                }
                            },
                            {
                                "id": "4f39f332e4b09642a19a8f0f",
                                "createdAt": 1329197874,
                                "text": "\u6771\u6d77\u9053\u7dda\u3082\u6a2a\u9808\u8cc0\u7dda\u3082\u505c\u307e\u308b\u4e0a\u306b\u3001\u6d45\u8349\u7dda\u3084\u3086\u308a\u304b\u3082\u3081\u306b\u4e57\u308a\u63db\u3048\u3089\u308c\u308b\u306e\u306b\u4eac\u6d5c\u6771\u5317\u7dda\u306e\u5feb\u901f\u306f\u901a\u904e\u3059\u308b\u3068\u3044\u3046\u3002",
                                "type": "user",
                                "canonicalUrl": "https://foursquare.com/item/4f39f332e4b09642a19a8f0f",
                                "lang": "ja",
                                "likes": {
                                    "count": 9,
                                    "groups": [
                                        {
                                            "type": "others",
                                            "count": 9,
                                            "items": [
                                                {
                                                    "id": "59067313",
                                                    "firstName": "\u3072\u3073\u304d\u3089\ud83c\udf65",
                                                    "lastName": "\u305b\u3044\u3053",
                                                    "handle": "hibikira01",
                                                    "privateProfile": false,
                                                    "gender": "male",
                                                    "address": "",
                                                    "city": "",
                                                    "state": "",
                                                    "countryCode": "JP",
                                                    "followingRelationship": "none",
                                                    "photo": {
                                                        "prefix": "https://fastly.4sqi.net/img/user/",
                                                        "suffix": "/59067313_GrF13AZH_qTN-0EsRvn_PtVqgTxo9Ld1peFznLR1x3EXZPGpif7_1OO7SfpU8RASMQGyb7_Mm.jpg"
                                                    }
                                                },
                                                {
                                                    "id": "3882352",
                                                    "firstName": "\u8ff7\u63a2\u5075P",
                                                    "handle": "meitantei_p",
                                                    "privateProfile": false,
                                                    "gender": "male",
                                                    "countryCode": "JP",
                                                    "followingRelationship": "none",
                                                    "photo": {
                                                        "prefix": "https://fastly.4sqi.net/img/user/",
                                                        "suffix": "/3882352_BKLEJAdB_FRzP1_47X5JKAfR8AEnLnAU68Mui86GA1HUs9L-aup6w6QXRiVKRR7b5kntT82V2.jpg"
                                                    }
                                                },
                                                {
                                                    "id": "6705545",
                                                    "firstName": "Shinichi",
                                                    "lastName": "Ishizaki",
                                                    "handle": "ishiki0210",
                                                    "privateProfile": false,
                                                    "gender": "male",
                                                    "countryCode": "JP",
                                                    "followingRelationship": "none",
                                                    "photo": {
                                                        "prefix": "https://fastly.4sqi.net/img/user/",
                                                        "suffix": "/blank_boy.png",
                                                        "default": true
                                                    }
                                                },
                                                {
                                                    "id": "1106662",
                                                    "firstName": "amethstos",
                                                    "handle": "amethstos",
                                                    "privateProfile": false,
                                                    "gender": "male",
                                                    "countryCode": "JP",
                                                    "followingRelationship": "none",
                                                    "photo": {
                                                        "prefix": "https://fastly.4sqi.net/img/user/",
                                                        "suffix": "/CHR4LDHUAS5KXHVS.jpg"
                                                    }
                                                }
                                            ]
                                        }
                                    ],
                                    "summary": "9 likes"
                                },
                                "like": false,
                                "logView": true,
                                "editedAt": 1410058956,
                                "agreeCount": 21,
                                "disagreeCount": 0,
                                "todo": {
                                    "count": 1
                                },
                                "user": {
                                    "id": "8531339",
                                    "firstName": "Culun",
                                    "handle": "culun_1st",
                                    "privateProfile": false,
                                    "gender": "male",
                                    "address": "",
                                    "city": "",
                                    "state": "",
                                    "countryCode": "JP",
                                    "followingRelationship": "none",
                                    "photo": {
                                        "prefix": "https://fastly.4sqi.net/img/user/",
                                        "suffix": "/8531339_XOo7FuzQ_WERTzenNZZ4QhAVXTw2HjCu9-xcIo2ap3vC9UE7Vy6GHWgQQGt134nDLNISp1k5_.jpg"
                                    }
                                }
                            },
                            {
                                "id": "4c8f0422d80976b03b808675",
                                "createdAt": 1284441122,
                                "text": "\u6771\u6d77\u9053\u7dda\u304b\u3089\u9280\u5ea7\u7dda\u3078\u306e\u4e57\u308a\u63db\u3048\u306f12\u53f7\u8eca\u3042\u305f\u308a\u304c\u6700\u77ed\u3002",
                                "type": "user",
                                "canonicalUrl": "https://foursquare.com/item/4c8f0422d80976b03b808675",
                                "lang": "ja",
                                "likes": {
                                    "count": 3,
                                    "groups": [
                                        {
                                            "type": "others",
                                            "count": 3,
                                            "items": [
                                                {
                                                    "id": "8004745",
                                                    "firstName": "watanabe81",
                                                    "handle": "watanabe81",
                                                    "privateProfile": false,
                                                    "gender": "none",
                                                    "countryCode": "JP",
                                                    "followingRelationship": "none",
                                                    "photo": {
                                                        "prefix": "https://fastly.4sqi.net/img/user/",
                                                        "suffix": "/XQP4QEN0YRGD0YPH.jpg"
                                                    }
                                                },
                                                {
                                                    "id": "2104919",
                                                    "firstName": "nozomi",
                                                    "handle": "nozomi_s",
                                                    "privateProfile": false,
                                                    "gender": "none",
                                                    "countryCode": "JP",
                                                    "followingRelationship": "none",
                                                    "photo": {
                                                        "prefix": "https://fastly.4sqi.net/img/user/",
                                                        "suffix": "/blank_boy.png",
                                                        "default": true
                                                    }
                                                },
                                                {
                                                    "id": "277274",
                                                    "firstName": "Tadashi",
                                                    "lastName": "Ogino",
                                                    "handle": "tadaogi",
                                                    "privateProfile": false,
                                                    "gender": "male",
                                                    "countryCode": "JP",
                                                    "followingRelationship": "none",
                                                    "photo": {
                                                        "prefix": "https://fastly.4sqi.net/img/user/",
                                                        "suffix": "/LBKJ3KXISBN0UHLZ.jpg"
                                                    }
                                                }
                                            ]
                                        }
                                    ],
                                    "summary": "3 likes"
                                },
                                "like": false,
                                "logView": true,
                                "agreeCount": 3,
                                "disagreeCount": 0,
                                "todo": {
                                    "count": 2
                                },
                                "user": {
                                    "id": "339974",
                                    "firstName": "Rumi",
                                    "handle": "room119",
                                    "privateProfile": false,
                                    "gender": "female",
                                    "countryCode": "AE",
                                    "followingRelationship": "none",
                                    "photo": {
                                        "prefix": "https://fastly.4sqi.net/img/user/",
                                        "suffix": "/IQZXRKLNNJFZHFWO.jpg"
                                    }
                                }
                            }
                        ]
                    }
                ]
            },
            "shortUrl": "http://4sq.com/ciWWw0",
            "timeZone": "Asia/Tokyo",
            "listed": {
                "count": 225,
                "groups": [
                    {
                        "type": "others",
                        "name": "Lists from other people",
                        "count": 225,
                        "items": [
                            {
                                "id": "4e4fe0cb62e14b77e3a204f6",
                                "name": "\u6771\u6d77\u9053\u672c\u7dda",
                                "description": "\u6771\u6d77\u9053\u672c\u7dda \u5168\u99c5\uff08\u300c\u6771\u6d77\u9053\u7dda\u5217\u8eca\u300d\u306e\u505c\u8eca\u99c5\u306e\u307f\uff09",
                                "type": "others",
                                "user": {
                                    "id": "252322",
                                    "firstName": "Izumi",
                                    "lastName": "Tomiyama",
                                    "handle": "nan_no_hi",
                                    "privateProfile": false,
                                    "gender": "none",
                                    "address": "",
                                    "city": "",
                                    "state": "",
                                    "countryCode": "JP",
                                    "followingRelationship": "none",
                                    "photo": {
                                        "prefix": "https://fastly.4sqi.net/img/user/",
                                        "suffix": "/O5GNSNUEVJBLRUWF.png"
                                    }
                                },
                                "editable": false,
                                "public": true,
                                "collaborative": false,
                                "url": "/nan_no_hi/list/%E6%9D%B1%E6%B5%B7%E9%81%93%E6%9C%AC%E7%B7%9A",
                                "canonicalUrl": "https://foursquare.com/nan_no_hi/list/%E6%9D%B1%E6%B5%B7%E9%81%93%E6%9C%AC%E7%B7%9A",
                                "createdAt": 1313857739,
                                "updatedAt": 1353248243,
                                "photo": {
                                    "id": "4dbb59d2fd285ccb6d285473",
                                    "createdAt": 1304123858,
                                    "prefix": "https://fastly.4sqi.net/img/general/",
                                    "suffix": "/5XLVP2WFBWYZ2AO2JPLMYQT5IQLGY0IP1C1Q55SHUYHSHJBT.jpg",
                                    "width": 540,
                                    "height": 720,
                                    "user": {
                                        "id": "2189339",
                                        "firstName": "Junichi",
                                        "lastName": "Sugiyama",
                                        "handle": "skywave_jp",
                                        "privateProfile": false,
                                        "gender": "male",
                                        "countryCode": "JP",
                                        "followingRelationship": "none",
                                        "photo": {
                                            "prefix": "https://fastly.4sqi.net/img/user/",
                                            "suffix": "/NZXGMOXSBPP5NFB3.jpg"
                                        }
                                    },
                                    "visibility": "public"
                                },
                                "followers": {
                                    "count": 297
                                },
                                "listItems": {
                                    "count": 154,
                                    "items": [
                                        {
                                            "id": "v4b600990f964a520e3d329e3",
                                            "createdAt": 1313857739,
                                            "photo": {
                                                "id": "50a5c5e2e4b04eb9cbd23b93",
                                                "createdAt": 1353041378,
                                                "prefix": "https://fastly.4sqi.net/img/general/",
                                                "suffix": "/1603433_jkgV3Hcz4Tctq1mmFx4lt-2N9zSEH1EX-3g0YqH1T-A.jpg",
                                                "width": 720,
                                                "height": 537,
                                                "user": {
                                                    "id": "1603433",
                                                    "firstName": "Kunio",
                                                    "lastName": "Fujii",
                                                    "handle": "kuniofujii",
                                                    "privateProfile": false,
                                                    "gender": "male",
                                                    "countryCode": "JP",
                                                    "followingRelationship": "none",
                                                    "photo": {
                                                        "prefix": "https://fastly.4sqi.net/img/user/",
                                                        "suffix": "/VRA1O2TMDMIPLCCS.jpg"
                                                    }
                                                },
                                                "visibility": "public"
                                            }
                                        }
                                    ]
                                }
                            },
                            {
                                "id": "4e4b849f7d8b6016b18931e5",
                                "name": "\u5c71\u624b\u7dda [JY]",
                                "description": "\u6771\u65e5\u672c\u65c5\u5ba2\u9244\u9053 https://www.jreast.co.jp/",
                                "entities": [
                                    {
                                        "indices": [
                                            8,
                                            33
                                        ],
                                        "type": "url",
                                        "object": {
                                            "url": "https://www.jreast.co.jp/"
                                        }
                                    }
                                ],
                                "type": "others",
                                "user": {
                                    "id": "271248",
                                    "firstName": "nakanao",
                                    "handle": "nakanao",
                                    "privateProfile": false,
                                    "gender": "male",
                                    "countryCode": "JP",
                                    "followingRelationship": "none",
                                    "photo": {
                                        "prefix": "https://fastly.4sqi.net/img/user/",
                                        "suffix": "/R35HQNUATXGFDCNL.jpg"
                                    }
                                },
                                "editable": false,
                                "public": true,
                                "collaborative": false,
                                "url": "/nakanao/list/%E5%B1%B1%E6%89%8B%E7%B7%9A-jy",
                                "canonicalUrl": "https://foursquare.com/nakanao/list/%E5%B1%B1%E6%89%8B%E7%B7%9A-jy",
                                "createdAt": 1313571999,
                                "updatedAt": 1584254704,
                                "photo": {
                                    "id": "4dd70abaa12d431f8bab01ac",
                                    "createdAt": 1305938618,
                                    "prefix": "https://fastly.4sqi.net/img/general/",
                                    "suffix": "/0PVGYFURTULL2Z1RLW4GSH1KXP1UYAPIP0IT3CO4KX3F3HBO.jpg",
                                    "width": 720,
                                    "height": 480,
                                    "user": {
                                        "id": "2106636",
                                        "firstName": "JP",
                                        "lastName": "malabares",
                                        "handle": "malabares88",
                                        "privateProfile": false,
                                        "gender": "male",
                                        "countryCode": "JP",
                                        "followingRelationship": "none",
                                        "photo": {
                                            "prefix": "https://fastly.4sqi.net/img/user/",
                                            "suffix": "/DVINM2HRBGMFR22I.jpg"
                                        }
                                    },
                                    "visibility": "public"
                                },
                                "followers": {
                                    "count": 401
                                },
                                "listItems": {
                                    "count": 30,
                                    "items": [
                                        {
                                            "id": "v4b600990f964a520e3d329e3",
                                            "createdAt": 1313571999,
                                            "photo": {
                                                "id": "4f92ae3de4b0949d2045dfd7",
                                                "createdAt": 1335012925,
                                                "prefix": "https://fastly.4sqi.net/img/general/",
                                                "suffix": "/bc0aDtFn-9HHMxXRSXcXrGhO7ywp1OCGYCLVLN7zbJE.jpg",
                                                "width": 537,
                                                "height": 720,
                                                "user": {
                                                    "id": "4219318",
                                                    "firstName": "Arrie",
                                                    "lastName": "Mulyadi",
                                                    "handle": "arrie31",
                                                    "privateProfile": false,
                                                    "gender": "none",
                                                    "countryCode": "ID",
                                                    "followingRelationship": "none",
                                                    "photo": {
                                                        "prefix": "https://fastly.4sqi.net/img/user/",
                                                        "suffix": "/B40XWVNVE3JZDS3N.jpg"
                                                    }
                                                },
                                                "visibility": "public"
                                            }
                                        }
                                    ]
                                }
                            }
                        ]
                    }
                ]
            },
            "phrases": [
                {
                    "phrase": "connecting station",
                    "sample": {
                        "entities": [
                            {
                                "indices": [
                                    10,
                                    28
                                ],
                                "type": "keyPhrase"
                            }
                        ],
                        "text": "This is a connecting station of Keio Line, Ginza Line and JR Line.. Have..."
                    },
                    "count": 2
                },
                {
                    "phrase": "\u6a2a\u9808\u8cc0\u7dda\u306e\u30db\u30fc\u30e0\u306f",
                    "sample": {
                        "entities": [
                            {
                                "indices": [
                                    0,
                                    9
                                ],
                                "type": "keyPhrase"
                            }
                        ],
                        "text": "\u6a2a\u9808\u8cc0\u7dda\u306e\u30db\u30fc\u30e0\u306f\u671d\u72ed\u3044\u306e\u3067\u6539\u672d\u307e\u3067\u306b\u6642\u9593\u304c\u304b\u304b\u308a\u307e\u3059\u3002\u6771\u4eac\u3084\u54c1\u5ddd\u304b\u3089\u8fc2\u56de\u3059\u308b\u306e\u3092\u30aa\u30b9\u30b9\u30e1\u3057\u307e\u3059\u3002"
                    },
                    "count": 2
                },
                {
                    "phrase": "\u6771\u6d77\u9053\u7dda\u304b\u3089",
                    "sample": {
                        "entities": [
                            {
                                "indices": [
                                    0,
                                    6
                                ],
                                "type": "keyPhrase"
                            }
                        ],
                        "text": "\u6771\u6d77\u9053\u7dda\u304b\u3089\u9280\u5ea7\u7dda\u3078\u306e\u4e57\u308a\u63db\u3048\u306f12\u53f7\u8eca\u3042\u305f\u308a\u304c\u6700\u77ed\u3002"
                    },
                    "count": 2
                }
            ],
            "popular": {
                "isOpen": false,
                "isLocalHoliday": false,
                "timeframes": [
                    {
                        "days": "Today",
                        "includesToday": true,
                        "open": [
                            {
                                "renderedTime": "10:00 AM\u20138:00 PM"
                            }
                        ],
                        "segments": []
                    },
                    {
                        "days": "Sun",
                        "open": [
                            {
                                "renderedTime": "11:00 AM\u20137:00 PM"
                            }
                        ],
                        "segments": []
                    },
                    {
                        "days": "Mon",
                        "open": [
                            {
                                "renderedTime": "8:00 AM\u201310:00 AM"
                            },
                            {
                                "renderedTime": "5:00 PM\u20139:00 PM"
                            }
                        ],
                        "segments": []
                    },
                    {
                        "days": "Tue",
                        "open": [
                            {
                                "renderedTime": "8:00 AM\u201310:00 AM"
                            },
                            {
                                "renderedTime": "5:00 PM\u201310:00 PM"
                            }
                        ],
                        "segments": []
                    },
                    {
                        "days": "Wed",
                        "open": [
                            {
                                "renderedTime": "8:00 AM\u201310:00 AM"
                            },
                            {
                                "renderedTime": "Noon\u20131:00 PM"
                            },
                            {
                                "renderedTime": "5:00 PM\u201310:00 PM"
                            }
                        ],
                        "segments": []
                    },
                    {
                        "days": "Thu",
                        "open": [
                            {
                                "renderedTime": "8:00 AM\u201310:00 AM"
                            },
                            {
                                "renderedTime": "Noon\u20131:00 PM"
                            },
                            {
                                "renderedTime": "5:00 PM\u201311:00 PM"
                            }
                        ],
                        "segments": []
                    },
                    {
                        "days": "Fri",
                        "open": [
                            {
                                "renderedTime": "8:00 AM\u201310:00 AM"
                            },
                            {
                                "renderedTime": "Noon\u20131:00 PM"
                            },
                            {
                                "renderedTime": "4:00 PM\u2013Midnight"
                            }
                        ],
                        "segments": []
                    }
                ]
            },
            "seasonalHours": [],
            "pageUpdates": {
                "count": 0
            },
            "inbox": {
                "count": 0,
                "items": []
            },
            "attributes": {
                "groups": [
                    {
                        "type": "payments",
                        "name": "Credit Cards",
                        "summary": "No Credit Cards",
                        "count": 5,
                        "items": [
                            {
                                "displayName": "Credit Cards",
                                "displayValue": "No"
                            }
                        ]
                    }
                ]
            },
            "bestPhoto": {
                "id": "5a812d5a66fc6509b7544bf5",
                "createdAt": 1518415194,
                "source": {
                    "name": "Swarm for iOS",
                    "url": "https://www.swarmapp.com"
                },
                "prefix": "https://fastly.4sqi.net/img/general/",
                "suffix": "/454721750_KNZ1sYqMcM5NQ8hlvoxeDeOQpHMwrBiofKcG7y9HHBk.jpg",
                "width": 1440,
                "height": 1920,
                "visibility": "public"
            }
        }
    }
}